Workbook

Sheet Final Project Dataset
A1: Transaction_ID | B1: Date | C1: Customer_ID | D1: Customer_Name | E1: Product_ID | F1: Product_Name | G1: Category | H1: Quantity | I1: Unit_Price | J1: Payment_Method | K1: Region | L1: Customer_Segment | M1: Customer_Since | N1: Total_Amount | O1: Timestamp | P1: Month | Q1: Year | R1: Customer_Years
A2: TRX0001 | B2: 2024-10-30 | C2: CUST005 | D2: Arthur Edwards | E2: P006 | F2: Office Chair | G2: Furniture | H2: 2 | I2: 199.99 | J2: Cash | K2: East | L2: Premium | M2: 2021-04-09 | N2: 399.98 | O2: 2026-05-15 15:09:00 | P2: Oct | Q2: 2024 | R2: 5
A3: TRX0002 | B3: 2024-07-29 | C3: CUST006 | D3: Mark Carter | E3: P001 | F3: Laptop | G3: Electronics | H3: 5 | I3: 899.99 | J3: PayPal | K3: North | L3: Basic | M3: 2021-03-18 | N3: 4499.95 | O3: 2026-05-15 15:09:00 | P3: Jul | Q3: 2024 | R3: 5
A4: TRX0003 | B4: 2024-11-14 | C4: CUST037 | D4: Kathleen Bennett | E4: P002 | F4: Smartphone | G4: Electronics | H4: 5 | I4: 699.99 | J4: Credit Card | K4: Central | L4: Basic | M4: 2021-05-02 | N4: 3499.95 | O4: 2026-05-15 15:09:00 | P4: Nov | Q4: 2024 | R4: 5
A5: TRX0004 | B5: 2024-10-31 | C5: CUST015 | D5: Joseph Jackson | E5: P010 | F5: Keyboard | G5: Electronics | H5: 5 | I5: 89.99 | J5: Credit Card | K5: East | L5: Standard | M5: 2021-04-12 | N5: 449.95 | O5: 2026-05-15 15:09:00 | P5: Oct | Q5: 2024 | R5: 5
A6: TRX0005 | B6: 2024-06-10 | C6: CUST020 | D6: Patricia Moore | E6: P003 | F6: Headphones | G6: Electronics | H6: 5 | I6: 149.99 | J6: Credit Card | K6: North | L6: Premium | M6: 2024-03-15 | N6: 749.95 | O6: 2026-05-15 15:09:00 | P6: Jun | Q6: 2024 | R6: 2
A7: TRX0006 | B7: 2024-10-18 | C7: CUST036 | D7: Margaret Wright | E7: P010 | F7: Keyboard | G7: Electronics | H7: 2 | I7: 89.99 | J7: Cash | K7: Central | L7: Basic | M7: 2021-07-19 | N7: 179.98 | O7: 2026-05-15 15:09:00 | P7: Oct | Q7: 2024 | R7: 4
A8: TRX0007 | B8: 2024-12-21 | C8: CUST028 | D8: Daniel King | E8: P010 | F8: Keyboard | G8: Electronics | H8: 2 | I8: 89.99 | J8: Debit Card | K8: West | L8: Premium | M8: 2023-12-25 | N8: 179.98 | O8: 2026-05-15 15:09:00 | P8: Dec | Q8: 2024 | R8: 2
A9: TRX0008 | B9: 2024-09-11 | C9: CUST012 | D9: Margaret Wright | E9: P008 | F9: Bookshelf | G9: Furniture | H9: 3 | I9: 149.99 | J9: Credit Card | K9: North | L9: Premium | M9: 2022-05-24 | N9: 449.97 | O9: 2026-05-15 15:09:00 | P9: Sep | Q9: 2024 | R9: 3
A10: TRX0009 | B10: 2024-12-20 | C10: CUST047 | D10: Maria Garcia | E10: P005 | F10: Blender | G10: Appliances | H10: 5 | I10: 59.99 | J10: Debit Card | K10: Central | L10: Basic | M10: 2022-12-05 | N10: 299.95 | O10: 2026-05-15 15:09:00 | P10: Dec | Q10: 2024 | R10: 3
A11: TRX0010 | B11: 2024-11-11 | C11: CUST049 | D11: Peter Richardson | E11: P002 | F11: Smartphone | G11: Electronics | H11: 5 | I11: 699.99 | J11: Credit Card | K11: West | L11: Standard | M11: 2021-12-04 | N11: 3499.95 | O11: 2026-05-15 15:09:00 | P11: Nov | Q11: 2024 | R11: 4
A12: TRX0011 | B12: 2025-01-21 | C12: CUST021 | D12: Peter Richardson | E12: P001 | F12: Laptop | G12: Electronics | H12: 1 | I12: 899.99 | J12: Debit Card | K12: Central | L12: Standard | M12: 2024-03-19 | N12: 899.99 | O12: 2026-05-15 15:09:00 | P12: Jan | Q12: 2025 | R12: 2
A13: TRX0012 | B13: 2024-05-16 | C13: CUST018 | D13: Virginia Sanders | E13: P010 | F13: Keyboard | G13: Electronics | H13: 4 | I13: 89.99 | J13: Cash | K13: North | L13: Premium | M13: 2021-07-11 | N13: 359.96 | O13: 2026-05-15 15:09:00 | P13: May | Q13: 2024 | R13: 4
... A217: TRX0216 | B217: 2024-05-21 | C217: CUST043 | D217: Helen Roberts | E217: P004 | F217: Coffee Maker | G217: Appliances | H217: 5 | I217: 79.99 | J217: Cash | K217: Central | L217: Basic | M217: 2023-06-18 | N217: 399.95 | O217: 2026-05-15 15:09:00 | P217: May | Q217: 2024 | R217: 2

Sheet Analysis
A1: Analysis
A3: Total Revenue | B3: =SUM('Final Project Dataset'!N2:N217) -> 205163.37 | D3: TODAY() | E3: =TODAY() -> 46157
A4: Average Revenue | B4: =AVERAGE('Final Project Dataset'!N2:N217) -> 949.83042 | D4: NOW() | E4: =NOW() -> 46157.862
A5: Total Transactions | B5: =COUNTA('Final Project Dataset'!A2:A217) -> 216 | D5: EOMONTH | E5: =EOMONTH(E3,0) -> 46173
A6: Top Customer | B6: =INDEX('Final Project Dataset'!D2:D217,MATCH(MAX('Final Project Dataset'!N2:N217),'Final Project Dataset'!N2:N217,0)) -> Mark Carter | D6: DATEDIF Years | E6: =DATEDIF("2021-01-01",TODAY(),"Y") -> 5
A7: Most Sold Product | B7: =INDEX('Final Project Dataset'!F2:F217,MATCH(MAX('Final Project Dataset'!H2:H217),'Final Project Dataset'!H2:H217,0)) -> Laptop
A10: WHAT-IF ANALYSIS | D10: FILTER FUNCTION
A11: Current Revenue | B11: =SUM('Final Project Dataset'!N2:N217) -> 205163.37 | D11: =_xlfn._xlws.FILTER('Final Project Dataset'!D2:D217,'Final Project Dataset'!K2:K217="West") -> Daniel King
A12: Increase % | B12: 0.15
A13: Projected Revenue | B13: =B11*(1+B12) -> 235937.88
D15: Customer Abbreviation | E15: =LEFT('Final Project Dataset'!D2,3)&"-"&RIGHT('Final Project Dataset'!C2,3) -> Art-005

Sheet Visualizations
A1: Region | B1: Sales | J1: Category | K1: Sales
A2: North | B2: =SUMIF('Final Project Dataset'!K:K,A2,'Final Project Dataset'!N:N) -> 39688.78 | J2: Electronics | K2: 55000
A3: South | B3: =SUMIF('Final Project Dataset'!K:K,A3,'Final Project Dataset'!N:N) -> 29458.81 | J3: Furniture | K3: 32000
A4: East | B4: =SUMIF('Final Project Dataset'!K:K,A4,'Final Project Dataset'!N:N) -> 39938.86 | J4: Appliances | K4: 18000
A5: West | B5: =SUMIF('Final Project Dataset'!K:K,A5,'Final Project Dataset'!N:N) -> 46508.48
A6: Central | B6: =SUMIF('Final Project Dataset'!K:K,A6,'Final Project Dataset'!N:N) -> 49568.44
A10: Month | B10: Revenue
A11: Apr | B11: 16666
A12: May | B12: 21731
A13: Jun | B13: 15673
A14: Jul | B14: 12565
A15: Aug | B15: 23507
A16: Sep | B16: 24157
A17: Oct | B17: 9915
A18: Nov | B18: 23871
A19: Dec | B19: 23305
A20: Jan | B20: 12732
A21: Feb | B21: 24101

Sheet Dashboard
A1: Dashboard
A3: Total Revenue | B3: =Analysis!B3 -> 205163.37
A5: Average Revenue | B5: =Analysis!B4 -> 949.83042
A7: Total Transactions | B7: =Analysis!B5 -> 216
A9: Top Customer | B9: =Analysis!B6 -> Mark Carter
A11: Most Sold Product | B11: =Analysis!B7 -> Laptop
